README.rst
setup.py
glsvg/__init__.py
glsvg/glutils.py
glsvg/gradient.py
glsvg/graphics.py
glsvg/lines.py
glsvg/render_target.py
glsvg/shader.py
glsvg/svg.py
glsvg/svg_constants.py
glsvg/svg_filter.py
glsvg/svg_parser_utils.py
glsvg/svg_path.py
glsvg/svg_path_builder.py
glsvg/svg_pattern.py
glsvg/svg_shader_constants.py
glsvg/svg_style.py
glsvg/vector_math.py
lat_lon_parser/__init__.py
lat_lon_parser/lat_long.py
lat_lon_parser/parser.py
lat_lon_parser/tests/__init__.py
lat_lon_parser/tests/test_lat_lon_parser.py
lat_lon_parser/tests/test_lat_long.py
omnivore_framework.egg-info/PKG-INFO
omnivore_framework.egg-info/SOURCES.txt
omnivore_framework.egg-info/dependency_links.txt
omnivore_framework.egg-info/not-zip-safe
omnivore_framework.egg-info/requires.txt
omnivore_framework.egg-info/top_level.txt
post_gnome/__init__.py
post_gnome/kmz_particles.py
post_gnome/make_layer_file.py
post_gnome/nc2shape.py
post_gnome/nc_particles.py
post_gnome/kml_stuff/MossSeries2Kmz.py
post_gnome/kml_stuff/__init__.py
post_gnome/kml_stuff/build64.py
post_gnome/kml_stuff/kml_templates.py
post_gnome/kml_stuff/moss2kmz.py
post_gnome/kml_stuff/moss_kml_templates.py
post_gnome/kml_stuff/write_kmz.py
post_gnome/plotting/__init__.py
post_gnome/plotting/geo_plots.py
post_gnome/readers/__init__.py
post_gnome/readers/read_moss.py
post_gnome/tests/__init__.py
post_gnome/tests/nc_particle_build_sample.py
post_gnome/tests/test_kmz_particles.py
post_gnome/tests/test_nc_particles.py
post_gnome/tests/test_nc_reader.py
post_gnome/tests/test_nc_writer.py
pyugrid/__init__.py
pyugrid/read_netcdf.py
pyugrid/ugrid.py
pyugrid/ugrid_wx.py
pyugrid/util.py
pyugrid/uvar.py
pyugrid/grid_io/__init__.py
pyugrid/grid_io/utils.py
pyugrid/test/__init__.py
pyugrid/test/test_add_data.py
pyugrid/test/test_find_nodes.py
pyugrid/test/test_find_uvar.py
pyugrid/test/test_grid_manipulation.py
pyugrid/test/test_io_util.py
pyugrid/test/test_locate_faces.py
pyugrid/test/test_point_in_triangle.py
pyugrid/test/test_read.py
pyugrid/test/test_save_as_netcdf.py
pyugrid/test/test_ugrid.py
pyugrid/test/test_util.py
pyugrid/test/test_uvar.py
pyugrid/test/test_write_read.py
pyugrid/test/utilities.py