Metadata-Version: 1.1
Name: omnivore-framework
Version: 4.0
Summary: Dependency target for mapping applications
Home-page: http://playermissile.com
Author: Rob McMullen
Author-email: feedback@playermissile.com
License: GPL
Download-URL: https://pypi.org/project/omnivore-framework/
Platform: Windows
Platform: Linux
Platform: Mac OS-X
Platform: Unix
Classifier: Development Status :: 5 - Production/Stable
Classifier: Intended Audience :: Developers
Classifier: License :: OSI Approved :: GNU General Public License (GPL)
Classifier: Operating System :: MacOS
Classifier: Operating System :: Microsoft :: Windows
Classifier: Operating System :: OS Independent
Classifier: Operating System :: POSIX
Classifier: Operating System :: Unix
Classifier: Programming Language :: Python
Classifier: Topic :: Utilities
Classifier: Topic :: Software Development :: Assemblers
Classifier: Topic :: Software Development :: Disassemblers
